pkg/__init__.py
pkg/__main__.py
pkg/auth.py
pkg/db_async.py
pkg/query.py
pkg/server.py
pkg/tests/__init__.py
pkg/tests/test_auth.py
pkg/tests/test_concurrency.py
pkg/tests/test_query.py
pkg/tests/test_websocket.py
sqlrooms_duckdb_server-0.2.2.dist-info/METADATA
sqlrooms_duckdb_server-0.2.2.dist-info/WHEEL
sqlrooms_duckdb_server-0.2.2.dist-info/entry_points.txt
sqlrooms_duckdb_server-0.2.2.dist-info/RECORD
