Metadata-Version: 2.4
Name: sqlrooms-duckdb-server
Version: 0.2.2
Summary: A DuckDB server for SQLRooms
Project-URL: homepage, https://github.com/sqlrooms/sqlrooms
Requires-Python: >=3.10
Requires-Dist: diskcache
Requires-Dist: duckdb<1.5.0,>=1.4.0
Requires-Dist: pandas
Requires-Dist: pyarrow
Requires-Dist: socketify
Requires-Dist: ujson
